buffering_async_logger/__init__.py
buffering_async_logger/caches.py
buffering_async_logger/handlers.py
buffering_async_logger/send_logs_utils.py
buffering_async_logger/timers.py
buffering_async_logger-0.1.4.dist-info/LICENSE
buffering_async_logger-0.1.4.dist-info/WHEEL
buffering_async_logger-0.1.4.dist-info/METADATA
buffering_async_logger-0.1.4.dist-info/RECORD
