Metadata-Version: 2.1
Name: buffering-async-logger
Version: 0.1.4
Summary: Helpers for sending logs to a destination in batches using a buffer in an async Python app.
Home-page: https://github.com/Jaza/buffering-async-logger
License: Apache-2.0
Author: Jeremy Epstein
Author-email: jazepstein@gmail.com
Requires-Python: >=3.10,<4
Classifier: License :: OSI Approved :: Apache Software License
Classifier: Programming Language :: Python :: 3
Classifier: Programming Language :: Python :: 3.10
Classifier: Programming Language :: Python :: 3.11
Requires-Dist: httpx
